setup.py
distributions_eselwhy/Binomialdistribution.py
distributions_eselwhy/Gaussiandistribution.py
distributions_eselwhy/Generaldistribution.py
distributions_eselwhy/__init__.py
distributions_eselwhy.egg-info/PKG-INFO
distributions_eselwhy.egg-info/SOURCES.txt
distributions_eselwhy.egg-info/dependency_links.txt
distributions_eselwhy.egg-info/not-zip-safe
distributions_eselwhy.egg-info/top_level.txt